lmcl/__init__.py
lmcl/lmcl.py
lmcl-0.1.3.dist-info/METADATA
lmcl-0.1.3.dist-info/WHEEL
lmcl-0.1.3.dist-info/top_level.txt
lmcl-0.1.3.dist-info/RECORD
