Metadata-Version: 2.1
Name: lmcl
Version: 0.1.3
Summary: A package designed to allow python users to communicate more effectively with LLMs via a microlang
Author: Isaac L.B Richardson
Requires-Dist: openai
